scripts/__init__.py
scripts/check_dependencies.py
scripts/compare_te.py
scripts/compile_dinov2.py
scripts/convert_dino_to_info_sharing.py
scripts/download_checkpoints.py
scripts/install_croco_rope.py
scripts/prepare_offline_install.py
scripts/validate_installation.py
uniception/__init__.py
uniception/models/__init__.py
uniception/models/encoders/README.md
uniception/models/encoders/__init__.py
uniception/models/encoders/base.py
uniception/models/encoders/cosmos.py
uniception/models/encoders/croco.py
uniception/models/encoders/dense_rep_encoder.py
uniception/models/encoders/dinov2.py
uniception/models/encoders/dinov3.py
uniception/models/encoders/dune.py
uniception/models/encoders/global_rep_encoder.py
uniception/models/encoders/image_normalizations.py
uniception/models/encoders/list.py
uniception/models/encoders/patch_embedder.py
uniception/models/encoders/perception_encoder.py
uniception/models/encoders/radio.py
uniception/models/encoders/utils.py
uniception/models/factory/__init__.py
uniception/models/factory/dust3r.py
uniception/models/info_sharing/README.md
uniception/models/info_sharing/__init__.py
uniception/models/info_sharing/alternating_attention_transformer.py
uniception/models/info_sharing/base.py
uniception/models/info_sharing/cross_attention_transformer.py
uniception/models/info_sharing/diff_cross_attention_transformer.py
uniception/models/info_sharing/global_attention_transformer.py
uniception/models/libs/README.md
uniception/models/libs/__init__.py
uniception/models/libs/cosmos_tokenizer/__init__.py
uniception/models/libs/cosmos_tokenizer/image_cli.py
uniception/models/libs/cosmos_tokenizer/image_lib.py
uniception/models/libs/cosmos_tokenizer/utils.py
uniception/models/libs/cosmos_tokenizer/video_cli.py
uniception/models/libs/cosmos_tokenizer/video_lib.py
uniception/models/libs/cosmos_tokenizer/modules/__init__.py
uniception/models/libs/cosmos_tokenizer/modules/distributions.py
uniception/models/libs/cosmos_tokenizer/modules/layers2d.py
uniception-0.1.6.dist-info/licenses/LICENSE
uniception-0.1.6.dist-info/METADATA
uniception-0.1.6.dist-info/WHEEL
uniception-0.1.6.dist-info/entry_points.txt
uniception-0.1.6.dist-info/top_level.txt
uniception-0.1.6.dist-info/RECORD
