Metadata-Version: 2.4
Name: uniception
Version: 0.1.6
Summary: Generalizable Perception Stack for 3D, 4D, spatial AI and scene understanding
Author-email: AirLab <airlab-dev@lists.andrew.cmu.edu>
License: BSD 3-Clause
Project-URL: Homepage, https://github.com/castacks/UniCeption
Project-URL: Bug Tracker, https://github.com/castacks/UniCeption/issues
Project-URL: Documentation, https://github.com/castacks/UniCeption/blob/main/README.md
Keywords: computer-vision,3d-vision,spatial-ai,perception,deep-learning,pytorch
Classifier: Development Status :: 3 - Alpha
Classifier: Intended Audience :: Developers
Classifier: Intended Audience :: Science/Research
Classifier: Programming Language :: Python :: 3
Classifier: Topic :: Scientific/Engineering :: Artificial Intelligence
Classifier: Topic :: Software Development :: Libraries :: Python Modules
Requires-Python: >=3.10
License-File: LICENSE
Requires-Dist: numpy
Requires-Dist: torch
Requires-Dist: torchvision
Requires-Dist: torchaudio
Requires-Dist: jaxtyping
Requires-Dist: matplotlib
Requires-Dist: Pillow
Requires-Dist: scikit-learn
Requires-Dist: einops
Requires-Dist: rerun-sdk
Requires-Dist: minio
Requires-Dist: torchmetrics
Requires-Dist: termcolor
Requires-Dist: timm
Provides-Extra: xformers
Requires-Dist: xformers; extra == "xformers"
Provides-Extra: dev
Requires-Dist: black; extra == "dev"
Requires-Dist: isort; extra == "dev"
Requires-Dist: pre-commit; extra == "dev"
Requires-Dist: pytest; extra == "dev"
Provides-Extra: all
Requires-Dist: xformers; extra == "all"
Requires-Dist: black; extra == "all"
Requires-Dist: isort; extra == "all"
Requires-Dist: pre-commit; extra == "all"
Requires-Dist: pytest; extra == "all"
Dynamic: license-file
